{"files":{"index.html":{"frameworks":["Landing Page","pg.tw.lib","pg.insight.events","pg.fontawesome.5","pg.ia.lib","pg.asset.manager","pg.svg.lib","pg.project.items","pg.ia","pg.code-validator","pg.image.overlay","pg.css.grid","tw","pg.html","pg.components"],"last_page_width":1086}},"breakpoints":["640px","768px","1024px","1280px","1536px"],"frameworks":["Landing Page","pg.tw.lib","pg.insight.events","pg.fontawesome.5","pg.ia.lib","pg.asset.manager","pg.svg.lib","pg.project.items","pg.ia","pg.code-validator","pg.image.overlay","pg.css.grid","tw","pg.html","pg.components"],"template_framework_id":"pg.tw.lib","urls":{"index.html":{"open-page-views":[{"w":1086,"h":0}]}},"active-design-provider":"tw","file-picker-copy-folder":"C:\\Users\\info\\Documents\\GitHub\\Alittletreat\\Landing Page\\Images","cs-for-overrides":"tailwind_theme/tailwind.css"}